odoo10_addon_sale_commission-10.0.2.6.0-nspkg.pth
odoo/addons/sale_commission/README.rst
odoo/addons/sale_commission/__init__.py
odoo/addons/sale_commission/__manifest__.py
odoo/addons/sale_commission/demo/sale_agent_demo.xml
odoo/addons/sale_commission/i18n/ca.po
odoo/addons/sale_commission/i18n/de.po
odoo/addons/sale_commission/i18n/es.po
odoo/addons/sale_commission/i18n/fr.po
odoo/addons/sale_commission/i18n/it.po
odoo/addons/sale_commission/i18n/pt.po
odoo/addons/sale_commission/i18n/pt_BR.po
odoo/addons/sale_commission/i18n/sale_commission.pot
odoo/addons/sale_commission/i18n/sl.po
odoo/addons/sale_commission/i18n/tr.po
odoo/addons/sale_commission/migrations/10.0.2.4.0/post-populate_company.py
odoo/addons/sale_commission/models/__init__.py
odoo/addons/sale_commission/models/account_invoice.py
odoo/addons/sale_commission/models/product_template.py
odoo/addons/sale_commission/models/res_partner.py
odoo/addons/sale_commission/models/sale_commission.py
odoo/addons/sale_commission/models/sale_commission_mixin.py
odoo/addons/sale_commission/models/sale_order.py
odoo/addons/sale_commission/models/settlement.py
odoo/addons/sale_commission/report/__init__.py
odoo/addons/sale_commission/report/sale_commission_analysis_report.py
odoo/addons/sale_commission/report/sale_commission_analysis_report_view.xml
odoo/addons/sale_commission/security/ir.model.access.csv
odoo/addons/sale_commission/security/security.xml
odoo/addons/sale_commission/static/description/icon.png
odoo/addons/sale_commission/static/description/icon.svg
odoo/addons/sale_commission/tests/__init__.py
odoo/addons/sale_commission/tests/test_sale_commission.py
odoo/addons/sale_commission/views/account_invoice_view.xml
odoo/addons/sale_commission/views/product_template_view.xml
odoo/addons/sale_commission/views/report_settlement_templates.xml
odoo/addons/sale_commission/views/res_partner_view.xml
odoo/addons/sale_commission/views/sale_commission_settlement_report.xml
odoo10_addon_sale_commission-10.0.2.6.0.dist-info/METADATA
odoo10_addon_sale_commission-10.0.2.6.0.dist-info/WHEEL
odoo10_addon_sale_commission-10.0.2.6.0.dist-info/namespace_packages.txt
odoo10_addon_sale_commission-10.0.2.6.0.dist-info/top_level.txt
odoo10_addon_sale_commission-10.0.2.6.0.dist-info/RECORD
