Metadata-Version: 2.1
Name: odoo10-addon-sale-commission
Version: 10.0.2.6.0
Summary: Sales commissions
Home-page: UNKNOWN
Author: Odoo Community Association (OCA),Tecnativa,AvanzOSC,Agile Business Group
Author-email: support@odoo-community.org
License: AGPL-3
Platform: UNKNOWN
Classifier: Programming Language :: Python
Classifier: Framework :: Odoo
Classifier: License :: OSI Approved :: GNU Affero General Public License v3
Requires-Python: ~=2.7
Requires-Dist: odoo (<10.1dev,>=10.0)
